{
    "Latin":"Sancte Míchael Archángele, defénde nos in proélio, contra nequítiam et insídias diáboli esto præsídium. Imperet illi Deus, súpplices deprecámur: tuque, Princeps milítiæ cæléstis, Sátanam aliósque spíritus malígnos, qui ad perditiónem animárum pervagántur in mundo, divína virtúte, in inférnum detrúde. Amen.",
    "English":"Saint Michael the Archangel, defend us in battle; be our defense against the wickedness and snares of the devil. May God rebuke him, we humbly pray. And do thou, O prince of the heavenly host, by the power of God thrust into hell Satan and all the evil spirits who prowl about the world for the ruin of souls. Amen.",
    "AudioFile":"SancteMichael.ogg",
    "EnglishName":"Saint Michael Prayer",
    "LatinName":"Sancte Míchael",
    "Groups":["Basic", "Mass", "Rosary"]
}
